byfax_sdk/ApiServiceCoverSoapClient.py
byfax_sdk/ApiServiceDocumentSoapClient.py
byfax_sdk/ApiServiceFaxoutSoapClient.py
byfax_sdk/ApiServiceInventorySoapClient.py
byfax_sdk/ApiServiceMessageSoapClient.py
byfax_sdk/FaxFile.py
byfax_sdk/__init__.py
byfax_sdk/models/ApiRequestFaxjobCountBroadcasts.py
byfax_sdk/models/ApiRequestFaxjobCountMessages.py
byfax_sdk/models/ApiRequestFaxjobMessage.py
byfax_sdk/models/ApiRequestFaxjobProcess.py
byfax_sdk/models/ApiRequestFaxjobSubmit.py
byfax_sdk/models/ApiRequestMessageCount.py
byfax_sdk/models/FaxContact.py
byfax_sdk/models/FaxGreeting.py
byfax_sdk/models/FaxMode.py
byfax_sdk/models/FaxQuality.py
byfax_sdk/models/FaxRecipient.py
byfax_sdk/models/ListPagination.py
byfax_sdk/models/__init__.py
byfax_sdk-1.1.0.dist-info/LICENSE
byfax_sdk-1.1.0.dist-info/METADATA
byfax_sdk-1.1.0.dist-info/WHEEL
byfax_sdk-1.1.0.dist-info/top_level.txt
byfax_sdk-1.1.0.dist-info/RECORD
