Metadata-Version: 2.1
Name: byfax-sdk
Version: 1.1.0
Summary: byFax Python SDK
Home-page: https://github.com/valconsultby/byfax-python
Author: ValConsultBy
Author-email: contact@pamconsult.by
License: UNKNOWN
Project-URL: Bug Tracker, https://github.com/valconsultby/byfax-python/issues
Platform: UNKNOWN
Classifier: Programming Language :: Python :: 3
Classifier: License :: OSI Approved :: MIT License
Classifier: Operating System :: OS Independent
Requires-Python: >=3.6
License-File: LICENSE
